<?xml version="1.0" encoding="windows-1252" ?>
<!DOCTYPE ViewLink SYSTEM "jbo_03_01.dtd">
<!---->
<ViewLink
  xmlns="http://xmlns.oracle.com/bc4j"
  Name="RoletoRoleVL"
  Version="12.2.1.12.24"
  InheritPersonalization="merge">
  <Properties>
    <SchemaBasedProperties>
      <LABEL
        ResId="model.UVO.RoletoRoleVL_LABEL"/>
    </SchemaBasedProperties>
  </Properties>
  <ViewLinkDefEnd
    Name="RolesTableU"
    Cardinality="1"
    Source="true"
    Owner="model.UVO.RolesTableUVO">
    <DesignTime>
      <Attr Name="_isUpdateable" Value="true"/>
      <Attr Name="_finderName" Value="RolesTableU"/>
    </DesignTime>
    <AttrArray Name="Attributes">
      <Item Value="model.UVO.RolesTableUVO.RoleName"/>
    </AttrArray>
  </ViewLinkDefEnd>
  <ViewLinkDefEnd
    Name="RoleNameRolesTableU"
    Cardinality="-1"
    Owner="model.UVO.RolesTableUVO">
    <DesignTime>
      <Attr Name="_isUpdateable" Value="true"/>
      <Attr Name="_finderName" Value="RoleNameRolesTableU"/>
    </DesignTime>
    <AttrArray Name="Attributes">
      <Item Value="model.UVO.RolesTableUVO.Id"/>
    </AttrArray>
  </ViewLinkDefEnd>
  <ResourceBundle>
    <PropertiesBundle
      PropertiesFile="model.ModelBundle"/>
  </ResourceBundle>
</ViewLink>
